langchain_gaimin/__init__.py
langchain_gaimin/langchain_embeddings.py
langchain_gaimin/langchain_gaimin_ai.py
langchain_gaimin-0.1.3.dist-info/LICENSE
langchain_gaimin-0.1.3.dist-info/METADATA
langchain_gaimin-0.1.3.dist-info/WHEEL
langchain_gaimin-0.1.3.dist-info/top_level.txt
langchain_gaimin-0.1.3.dist-info/RECORD
