Metadata-Version: 2.1
Name: langchain_gaimin
Version: 0.1.3
Summary: A Python client for Langchain GAIMIN API
Home-page: https://github.com/litthub-stuff/ai-langchain-gaimin-pyhton
Author: GAIMIN AI
Author-email: 
License: BSD-3-Clause
Classifier: Development Status :: 3 - Alpha
Classifier: Intended Audience :: Developers
Classifier: Operating System :: OS Independent
Classifier: Programming Language :: Python :: 3.6
Classifier: Programming Language :: Python :: 3.7
Classifier: Programming Language :: Python :: 3.8
Classifier: Programming Language :: Python :: 3.9
Classifier: Programming Language :: Python :: 3.10
Classifier: Programming Language :: Python :: 3.11
Classifier: Programming Language :: Python :: 3.12
Requires-Python: >=3.6
License-File: LICENSE
Requires-Dist: langchain-ollama >=0.2.0
